hardspheres_2d-0.1.0.dist-info/METADATA
hardspheres_2d-0.1.0.dist-info/WHEEL
hardspheres_2d-0.1.0.dist-info/entry_points.txt
hardspheres_2d-0.1.0.dist-info/licenses/LICENSE
hardspheres_2d/_core.pyi
hardspheres_2d/util.py
hardspheres_2d/__init__.py
hardspheres_2d/dump.py
hardspheres_2d/hex.py
hardspheres_2d/cli.py
hardspheres_2d/py.typed
hardspheres_2d/psi6.py
hardspheres_2d/_core.abi3.so
hardspheres_2d-0.1.0.dist-info/RECORD
