Metadata-Version: 2.4
Name: hardspheres-2d
Version: 0.1.0
Requires-Dist: click>=8.1.8
Requires-Dist: numpy>=2.2.4
Requires-Dist: polars>=1.25.2
Requires-Dist: scipy>=1.15.2
Requires-Dist: seaborn>=0.13.2
Requires-Dist: tqdm>=4.67.1
License-File: LICENSE
Summary: Add your description here
Author-email: eschmidt42 <11818904+eschmidt42@users.noreply.github.com>
Requires-Python: >=3.13
